function_addons/__init__.py
function_addons/request.py
do_function_addons-0.1.2.dist-info/METADATA
do_function_addons-0.1.2.dist-info/WHEEL
do_function_addons-0.1.2.dist-info/top_level.txt
do_function_addons-0.1.2.dist-info/RECORD
