Metadata-Version: 2.1
Name: do-function-addons
Version: 0.1.2
Summary: DigitalOcean functions addons. Typed Event and Context class.
Requires-Python: >3.8
